top_module_clk.v

module top_module_clk(
    input clk,
    input reset,
    input ena,
    output reg pm,
    output reg  [7:0] hh,
    output reg [7:0] mm,
    output  reg [7:0] ss); 


wire ena_ss,ena_mm,ena_hh,resetss,resetmm,resethh;
    wire  [7:0] hhh,mmm,sss;
    reg [5:0] load;
    reg [23:0] d;
    
    always @(*) begin         //posedge clk will not cme in senstivity list 
         ss<=sss;
         mm<=mmm;
         hh<=hhh;
        if(reset) begin
            // pm<=0;
            load<=6'b111111;
            d<=24'h120000;
              
        end
        else if(ena & ({hh,mm,ss}=={8'h11,8'h59,8'h59}))begin
            load<=6'b110000;
            d<=24'h120000;     
        end
        else if(ena & ({hh,mm,ss}=={8'h12,8'h59,8'h59}))begin
          //  pm<=~pm;                  //causing infinte time
            load<=6'b110000;
            d<=24'h010000;     
        end
        else begin
            load<=0;
        end
    end
    
    always @(posedge clk) begin 
        pm <= (ena & ({hh,mm,ss}=={8'h11,8'h59,8'h59}))^pm;
    end


    
    assign ena_ss = sss[0] & sss[3] ;
    assign resetss = (sss==8'h59)?1'b1:1'b0; 
    bcd_counter ss0 (clk,resetss,load[0],d[3:0],ena,sss[3:0]);
    bcd_counter ss1 (clk,resetss,load[1],d[7:4],(ena_ss & ena),sss[7:4]);
    
    assign ena_mm = mmm[0] & mmm[3] & resetss;
    assign  resetmm = ((mmm==8'h59) & resetss)?1'b1:1'b0;
    bcd_counter mm0 (clk,resetmm,load[2],d[11:8],(resetss & ena),mmm[3:0]);
    bcd_counter mm1 (clk,resetmm,load[3],d[15:12],(ena_mm & ena),mmm[7:4]);
    
    assign ena_hh = hhh[0] & hhh[3] & resetss & resetmm;
   // assign resethh = (hhh==8'h12)?1:0; 
    bcd_counter hh0 (clk,resethh,load[4],d[19:16],(resetmm & ena),hhh[3:0]);
    bcd_counter hh1 (clk,resethh,load[5],d[23:20],(ena_hh & ena),hhh[7:4]);
    
    
endmodule

module bcd_counter(
input clk,
input reset,
input load,
input [3:0] d,
input enable,
output reg [3:0] q);
    always @(posedge clk) begin
        if(reset | (q==9 & enable))
            q<=0;
        else if(load)
            q<=d;
        else if(enable)
            q<=q+1;  
    end
endmodule

tb_top_module_clk.v
`timescale 1ns/1ps
module tb_top_module_clk();

    // Inputs
    reg clk;
    reg reset;
    reg ena;

    // Outputs
   
    wire pm;
    wire [7:0] hh;
    wire [7:0] mm;
    wire [7:0] ss;

    // Instantiate the clock module
    top_module_clk dut (   clk,
     reset,
     ena,
     pm,
     hh,
     mm,
     ss
    );

always #5 clk=~clk;

    // Testbench stimulus
    initial begin
clk<= 0;
        reset <= 1'b0;
        ena <= 1'b0;
  end



initial begin
$dumpfile ("tb_result.vcd");
$dumpvars (0, tb_top_module_clk);
#7
           reset <= 1'b1;
        ena <= 1'b0;
        // Reset and wait for a few clock cycles
        #12 reset <= 1'b0;

        // Enable the clock module
        ena <= 1'b1;

        // Wait for some time to see the clock changes
        #200000;

        // Disable the clock module
        ena <= 1'b0;

        // Finish simulation
        $finish;
    end

endmodule

tb_result.vcd
$date
	Mon Aug 21 23:02:04 2023
$end
$version
	Icarus Verilog
$end
$timescale
	1ps
$end
$scope module tb_top_module_clk $end
$var wire 8 ! ss [7:0] $end
$var wire 1 " pm $end
$var wire 8 # mm [7:0] $end
$var wire 8 $ hh [7:0] $end
$var reg 1 % clk $end
$var reg 1 & ena $end
$var reg 1 ' reset $end
$scope module dut $end
$var wire 1 % clk $end
$var wire 1 & ena $end
$var wire 1 ( ena_hh $end
$var wire 1 ) ena_mm $end
$var wire 1 * ena_ss $end
$var wire 1 ' reset $end
$var wire 1 + resethh $end
$var wire 8 , sss [7:0] $end
$var wire 1 - resetss $end
$var wire 1 . resetmm $end
$var wire 8 / mmm [7:0] $end
$var wire 8 0 hhh [7:0] $end
$var reg 24 1 d [23:0] $end
$var reg 8 2 hh [7:0] $end
$var reg 6 3 load [5:0] $end
$var reg 8 4 mm [7:0] $end
$var reg 1 " pm $end
$var reg 8 5 ss [7:0] $end
$scope module hh0 $end
$var wire 1 % clk $end
$var wire 4 6 d [3:0] $end
$var wire 1 7 enable $end
$var wire 1 8 load $end
$var wire 1 + reset $end
$var reg 4 9 q [3:0] $end
$upscope $end
$scope module hh1 $end
$var wire 1 % clk $end
$var wire 4 : d [3:0] $end
$var wire 1 ; enable $end
$var wire 1 < load $end
$var wire 1 + reset $end
$var reg 4 = q [3:0] $end
$upscope $end
$scope module mm0 $end
$var wire 1 % clk $end
$var wire 4 > d [3:0] $end
$var wire 1 ? enable $end
$var wire 1 @ load $end
$var wire 1 . reset $end
$var reg 4 A q [3:0] $end
$upscope $end
$scope module mm1 $end
$var wire 1 % clk $end
$var wire 4 B d [3:0] $end
$var wire 1 C enable $end
$var wire 1 D load $end
$var wire 1 . reset $end
$var reg 4 E q [3:0] $end
$upscope $end
$scope module ss0 $end
$var wire 1 % clk $end
$var wire 4 F d [3:0] $end
$var wire 1 & enable $end
$var wire 1 G load $end
$var wire 1 - reset $end
$var reg 4 H q [3:0] $end
$upscope $end
$scope module ss1 $end
$var wire 1 % clk $end
$var wire 4 I d [3:0] $end
$var wire 1 J enable $end
$var wire 1 K load $end
$var wire 1 - reset $end
$var reg 4 L q [3:0] $end
$upscope $end
$upscope $end
$upscope $end
$enddefinitions $end
#0
$dumpvars
bx L
0K
0J
bx I
bx H
0G
bx F
bx E
0D
0C
bx B
bx A
0@
0?
bx >
bx =
0<
0;
bx :
bx 9
08
07
bx 6
bx 5
bx 4
b0 3
bx 2
bx 1
bx 0
bx /
x.
x-
bx ,
z+
x*
x)
x(
0'
0&
0%
bx $
bx #
x"
bx !
$end
#5000
1%
#7000
b0 F
b0 I
b0 >
b0 B
b10 6
b1 :
1G
1K
1@
1D
18
1<
b100100000000000000000 1
b111111 3
1'
#10000
0%
#15000
b10010 $
b10010 2
b0 #
b0 4
b0 !
b0 5
0(
0.
0)
0*
0-
b1 =
b10010 0
b10 9
b0 E
b0 /
b0 A
b0 L
b0 ,
b0 H
1%
#19000
0G
0K
0@
0D
08
0<
b0 3
1&
0'
#20000
0%
#25000
b1 !
b1 5
b1 ,
b1 H
1%
#30000
0%
#35000
b10 !
b10 5
b10 ,
b10 H
1%
#40000
0%
#45000
b11 !
b11 5
b11 ,
b11 H
1%
#50000
0%
#55000
b100 !
b100 5
b100 ,
b100 H
1%
#60000
0%
#65000
b101 !
b101 5
b101 ,
b101 H
1%
#70000
0%
#75000
b110 !
b110 5
b110 ,
b110 H
1%
#80000
0%
#85000
b111 !
b111 5
b111 ,
b111 H
1%
#90000
0%
#95000
b1000 !
b1000 5
b1000 ,
b1000 H
1%
#100000
0%
#105000
b1001 !
b1001 5
1J
1*
b1001 ,
b1001 H
1%
#110000
0%
#115000
b10000 !
b10000 5
0J
0*
b1 L
b10000 ,
b0 H
1%
#120000
0%
#125000
b10001 !
b10001 5
b10001 ,
b1 H
1%
#130000
0%
#135000
b10010 !
b10010 5
b10010 ,
b10 H
1%
#140000
0%
#145000
b10011 !
b10011 5
b10011 ,
b11 H
1%
#150000
0%
#155000
b10100 !
b10100 5
b10100 ,
b100 H
1%
#160000
0%
#165000
b10101 !
b10101 5
b10101 ,
b101 H
1%
#170000
0%
#175000
b10110 !
b10110 5
b10110 ,
b110 H
1%
#180000
0%
#185000
b10111 !
b10111 5
b10111 ,
b111 H
1%
#190000
0%
#195000
b11000 !
b11000 5
b11000 ,
b1000 H
1%
#200000
0%
#205000
b11001 !
b11001 5
1J
1*
b11001 ,
b1001 H
1%
#210000
0%
#215000
b100000 !
b100000 5
0J
0*
b10 L
b100000 ,
b0 H
1%
#220000
0%
#225000
b100001 !
b100001 5
b100001 ,
b1 H
1%
#230000
0%
#235000
b100010 !
b100010 5
b100010 ,
b10 H
1%
#240000
0%
#245000
b100011 !
b100011 5
b100011 ,
b11 H
1%
#250000
0%
#255000
b100100 !
b100100 5
b100100 ,
b100 H
1%
#260000
0%
#265000
b100101 !
b100101 5
b100101 ,
b101 H
1%
#270000
0%
#275000
b100110 !
b100110 5
b100110 ,
b110 H
1%
#280000
0%
#285000
b100111 !
b100111 5
b100111 ,
b111 H
1%
#290000
0%
#295000
b101000 !
b101000 5
b101000 ,
b1000 H
1%
#300000
0%
#305000
b101001 !
b101001 5
1J
1*
b101001 ,
b1001 H
1%
#310000
0%
#315000
b110000 !
b110000 5
0J
0*
b11 L
b110000 ,
b0 H
1%
#320000
0%
#325000
b110001 !
b110001 5
b110001 ,
b1 H
1%
#330000
0%
#335000
b110010 !
b110010 5
b110010 ,
b10 H
1%
#340000
0%
#345000
b110011 !
b110011 5
b110011 ,
b11 H
1%
#350000
0%
#355000
b110100 !
b110100 5
b110100 ,
b100 H
1%
#360000
0%
#365000
b110101 !
b110101 5
b110101 ,
b101 H
1%
#370000
0%
#375000
b110110 !
b110110 5
b110110 ,
b110 H
1%
#380000
0%
#385000
b110111 !
b110111 5
b110111 ,
b111 H
1%
#390000
0%
#395000
b111000 !
b111000 5
b111000 ,
b1000 H
1%
#400000
0%
#405000
b111001 !
b111001 5
1J
1*
b111001 ,
b1001 H
1%
#410000
0%
#415000
b1000000 !
b1000000 5
0J
0*
b100 L
b1000000 ,
b0 H
1%
#420000
0%
#425000
b1000001 !
b1000001 5
b1000001 ,
b1 H
1%
#430000
0%
#435000
b1000010 !
b1000010 5
b1000010 ,
b10 H
1%
#440000
0%
#445000
b1000011 !
b1000011 5
b1000011 ,
b11 H
1%
#450000
0%
#455000
b1000100 !
b1000100 5
b1000100 ,
b100 H
1%
#460000
0%
#465000
b1000101 !
b1000101 5
b1000101 ,
b101 H
1%
#470000
0%
#475000
b1000110 !
b1000110 5
b1000110 ,
b110 H
1%
#480000
0%
#485000
b1000111 !
b1000111 5
b1000111 ,
b111 H
1%
#490000
0%
#495000
b1001000 !
b1001000 5
b1001000 ,
b1000 H
1%
#500000
0%
#505000
b1001001 !
b1001001 5
1J
1*
b1001001 ,
b1001 H
1%
#510000
0%
#515000
b1010000 !
b1010000 5
0J
0*
b101 L
b1010000 ,
b0 H
1%
#520000
0%
#525000
b1010001 !
b1010001 5
b1010001 ,
b1 H
1%
#530000
0%
#535000
b1010010 !
b1010010 5
b1010010 ,
b10 H
1%
#540000
0%
#545000
b1010011 !
b1010011 5
b1010011 ,
b11 H
1%
#550000
0%
#555000
b1010100 !
b1010100 5
b1010100 ,
b100 H
1%
#560000
0%
#565000
b1010101 !
b1010101 5
b1010101 ,
b101 H
1%
#570000
0%
#575000
b1010110 !
b1010110 5
b1010110 ,
b110 H
1%
#580000
0%
#585000
b1010111 !
b1010111 5
b1010111 ,
b111 H
1%
#590000
0%
#595000
b1011000 !
b1011000 5
b1011000 ,
b1000 H
1%
#600000
0%
#605000
b1011001 !
b1011001 5
1J
1?
1*
1-
b1011001 ,
b1001 H
1%
#610000
0%
#615000
b1 #
b1 4
b0 !
b0 5
0J
0?
0*
0-
b1 /
b1 A
b0 L
b0 ,
b0 H
1%
#620000
0%
#625000
b1 !
b1 5
b1 ,
b1 H
1%
#630000
0%
#635000
b10 !
b10 5
b10 ,
b10 H
1%
#640000
0%
#645000
b11 !
b11 5
b11 ,
b11 H
1%
#650000
0%
#655000
b100 !
b100 5
b100 ,
b100 H
1%
#660000
0%
#665000
b101 !
b101 5
b101 ,
b101 H
1%
#670000
0%
#675000
b110 !
b110 5
b110 ,
b110 H
1%
#680000
0%
#685000
b111 !
b111 5
b111 ,
b111 H
1%
#690000
0%
#695000
b1000 !
b1000 5
b1000 ,
b1000 H
1%
#700000
0%
#705000
b1001 !
b1001 5
1J
1*
b1001 ,
b1001 H
1%
#710000
0%
#715000
b10000 !
b10000 5
0J
0*
b1 L
b10000 ,
b0 H
1%
#720000
0%
#725000
b10001 !
b10001 5
b10001 ,
b1 H
1%
#730000
0%
#735000
b10010 !
b10010 5
b10010 ,
b10 H
1%
#740000
0%
#745000
b10011 !
b10011 5
b10011 ,
b11 H
1%
#750000
0%
#755000
b10100 !
b10100 5
b10100 ,
b100 H
1%
#760000
0%
#765000
b10101 !
b10101 5
b10101 ,
b101 H
1%
#770000
0%
#775000
b10110 !
b10110 5
b10110 ,
b110 H
1%
#780000
0%
#785000
b10111 !
b10111 5
b10111 ,
b111 H
1%
#790000
0%
#795000
b11000 !
b11000 5
b11000 ,
b1000 H
1%
#800000
0%
#805000
b11001 !
b11001 5
1J
1*
b11001 ,
b1001 H
1%
#810000
0%
#815000
b100000 !
b100000 5
0J
0*
b10 L
b100000 ,
b0 H
1%
#820000
0%
#825000
b100001 !
b100001 5
b100001 ,
b1 H
1%
#830000
0%
#835000
b100010 !
b100010 5
b100010 ,
b10 H
1%
#840000
0%
#845000
b100011 !
b100011 5
b100011 ,
b11 H
1%
#850000
0%
#855000
b100100 !
b100100 5
b100100 ,
b100 H
1%
#860000
0%
#865000
b100101 !
b100101 5
b100101 ,
b101 H
1%
#870000
0%
#875000
b100110 !
b100110 5
b100110 ,
b110 H
1%
#880000
0%
#885000
b100111 !
b100111 5
b100111 ,
b111 H
1%
#890000
0%
#895000
b101000 !
b101000 5
b101000 ,
b1000 H
1%
#900000
0%
#905000
b101001 !
b101001 5
1J
1*
b101001 ,
b1001 H
1%
#910000
0%
#915000
b110000 !
b110000 5
0J
0*
b11 L
b110000 ,
b0 H
1%
#920000
0%
#925000
b110001 !
b110001 5
b110001 ,
b1 H
1%
#930000
0%
#935000
b110010 !
b110010 5
b110010 ,
b10 H
1%
#940000
0%
#945000
b110011 !
b110011 5
b110011 ,
b11 H
1%
#950000
0%
#955000
b110100 !
b110100 5
b110100 ,
b100 H
1%
#960000
0%
#965000
b110101 !
b110101 5
b110101 ,
b101 H
1%
#970000
0%
#975000
b110110 !
b110110 5
b110110 ,
b110 H
1%
#980000
0%
#985000
b110111 !
b110111 5
b110111 ,
b111 H
1%
#990000
0%
#995000
b111000 !
b111000 5
b111000 ,
b1000 H
1%
#1000000
0%
#1005000
b111001 !
b111001 5
1J
1*
b111001 ,
b1001 H
1%
#1010000
0%
#1015000
b1000000 !
b1000000 5
0J
0*
b100 L
b1000000 ,
b0 H
1%
#1020000
0%
#1025000
b1000001 !
b1000001 5
b1000001 ,
b1 H
1%
#1030000
0%
#1035000
b1000010 !
b1000010 5
b1000010 ,
b10 H
1%
#1040000
0%
#1045000
b1000011 !
b1000011 5
b1000011 ,
b11 H
1%
#1050000
0%
#1055000
b1000100 !
b1000100 5
b1000100 ,
b100 H
1%
#1060000
0%
#1065000
b1000101 !
b1000101 5
b1000101 ,
b101 H
1%
#1070000
0%
#1075000
b1000110 !
b1000110 5
b1000110 ,
b110 H
1%
#1080000
0%
#1085000
b1000111 !
b1000111 5
b1000111 ,
b111 H
1%
#1090000
0%
#1095000
b1001000 !
b1001000 5
b1001000 ,
b1000 H
1%
#1100000
0%
#1105000
b1001001 !
b1001001 5
1J
1*
b1001001 ,
b1001 H
1%
#1110000
0%
#1115000
b1010000 !
b1010000 5
0J
0*
b101 L
b1010000 ,
b0 H
1%
#1120000
0%
#1125000
b1010001 !
b1010001 5
b1010001 ,
b1 H
1%
#1130000
0%
#1135000
b1010010 !
b1010010 5
b1010010 ,
b10 H
1%
#1140000
0%
#1145000
b1010011 !
b1010011 5
b1010011 ,
b11 H
1%
#1150000
0%
#1155000
b1010100 !
b1010100 5
b1010100 ,
b100 H
1%
#1160000
0%
#1165000
b1010101 !
b1010101 5
b1010101 ,
b101 H
1%
#1170000
0%
#1175000
b1010110 !
b1010110 5
b1010110 ,
b110 H
1%
#1180000
0%
#1185000
b1010111 !
b1010111 5
b1010111 ,
b111 H
1%
#1190000
0%
#1195000
b1011000 !
b1011000 5
b1011000 ,
b1000 H
1%
#1200000
0%
#1205000
b1011001 !
b1011001 5
1J
1?
1*
1-
b1011001 ,
b1001 H
1%
#1210000
0%
#1215000
b10 #
b10 4
b0 !
b0 5
0J
0?
0*
0-
b10 /
b10 A
b0 L
b0 ,
b0 H
1%
#1220000
0%
#1225000
b1 !
b1 5
b1 ,
b1 H
1%
#1230000
0%
#1235000
b10 !
b10 5
b10 ,
b10 H
1%
#1240000
0%
#1245000
b11 !
b11 5
b11 ,
b11 H
1%
#1250000
0%
#1255000
b100 !
b100 5
b100 ,
b100 H
1%
#1260000
0%
#1265000
b101 !
b101 5
b101 ,
b101 H
1%
#1270000
0%
#1275000
b110 !
b110 5
b110 ,
b110 H
1%
#1280000
0%
#1285000
b111 !
b111 5
b111 ,
b111 H
1%
#1290000
0%
#1295000
b1000 !
b1000 5
b1000 ,
b1000 H
1%
#1300000
0%
#1305000
b1001 !
b1001 5
1J
1*
b1001 ,
b1001 H
1%
#1310000
0%
#1315000
b10000 !
b10000 5
0J
0*
b1 L
b10000 ,
b0 H
1%
#1320000
0%
#1325000
b10001 !
b10001 5
b10001 ,
b1 H
1%
#1330000
0%
#1335000
b10010 !
b10010 5
b10010 ,
b10 H
1%
#1340000
0%
#1345000
b10011 !
b10011 5
b10011 ,
b11 H
1%
#1350000
0%
#1355000
b10100 !
b10100 5
b10100 ,
b100 H
1%
#1360000
0%
#1365000
b10101 !
b10101 5
b10101 ,
b101 H
1%
#1370000
0%
#1375000
b10110 !
b10110 5
b10110 ,
b110 H
1%
#1380000
0%
#1385000
b10111 !
b10111 5
b10111 ,
b111 H
1%
#1390000
0%
#1395000
b11000 !
b11000 5
b11000 ,
b1000 H
1%
#1400000
0%
#1405000
b11001 !
b11001 5
1J
1*
b11001 ,
b1001 H
1%
#1410000
0%
#1415000
b100000 !
b100000 5
0J
0*
b10 L
b100000 ,
b0 H
1%
#1420000
0%
#1425000
b100001 !
b100001 5
b100001 ,
b1 H
1%
#1430000
0%
#1435000
b100010 !
b100010 5
b100010 ,
b10 H
1%
#1440000
0%
#1445000
b100011 !
b100011 5
b100011 ,
b11 H
1%
#1450000
0%
#1455000
b100100 !
b100100 5
b100100 ,
b100 H
1%
#1460000
0%
#1465000
b100101 !
b100101 5
b100101 ,
b101 H
1%
#1470000
0%
#1475000
b100110 !
b100110 5
b100110 ,
b110 H
1%
#1480000
0%
#1485000
b100111 !
b100111 5
b100111 ,
b111 H
1%
#1490000
0%
#1495000
b101000 !
b101000 5
b101000 ,
b1000 H
1%
#1500000
0%
#1505000
b101001 !
b101001 5
1J
1*
b101001 ,
b1001 H
1%
#1510000
0%
#1515000
b110000 !
b110000 5
0J
0*
b11 L
b110000 ,
b0 H
1%
#1520000
0%
#1525000
b110001 !
b110001 5
b110001 ,
b1 H
1%
#1530000
0%
#1535000
b110010 !
b110010 5
b110010 ,
b10 H
1%
#1540000
0%
#1545000
b110011 !
b110011 5
b110011 ,
b11 H
1%
#1550000
0%
#1555000
b110100 !
b110100 5
b110100 ,
b100 H
1%
#1560000
0%
#1565000
b110101 !
b110101 5
b110101 ,
b101 H
1%
#1570000
0%
#1575000
b110110 !
b110110 5
b110110 ,
b110 H
1%
#1580000
0%
#1585000
b110111 !
b110111 5
b110111 ,
b111 H
1%
#1590000
0%
#1595000
b111000 !
b111000 5
b111000 ,
b1000 H
1%
#1600000
0%
#1605000
b111001 !
b111001 5
1J
1*
b111001 ,
b1001 H
1%
#1610000
0%
#1615000
b1000000 !
b1000000 5
0J
0*
b100 L
b1000000 ,
b0 H
1%
#1620000
0%
#1625000
b1000001 !
b1000001 5
b1000001 ,
b1 H
1%
#1630000
0%
#1635000
b1000010 !
b1000010 5
b1000010 ,
b10 H
1%
#1640000
0%
#1645000
b1000011 !
b1000011 5
b1000011 ,
b11 H
1%
#1650000
0%
#1655000
b1000100 !
b1000100 5
b1000100 ,
b100 H
1%
#1660000
0%
#1665000
b1000101 !
b1000101 5
b1000101 ,
b101 H
1%
#1670000
0%
#1675000
b1000110 !
b1000110 5
b1000110 ,
b110 H
1%
#1680000
0%
#1685000
b1000111 !
b1000111 5
b1000111 ,
b111 H
1%
#1690000
0%
#1695000
b1001000 !
b1001000 5
b1001000 ,
b1000 H
1%
#1700000
0%
#1705000
b1001001 !
b1001001 5
1J
1*
b1001001 ,
b1001 H
1%
#1710000
0%
#1715000
b1010000 !
b1010000 5
0J
0*
b101 L
b1010000 ,
b0 H
1%
#1720000
0%
#1725000
b1010001 !
b1010001 5
b1010001 ,
b1 H
1%
#1730000
0%
#1735000
b1010010 !
b1010010 5
b1010010 ,
b10 H
1%
#1740000
0%
#1745000
b1010011 !
b1010011 5
b1010011 ,
b11 H
1%
#1750000
0%
#1755000
b1010100 !
b1010100 5
b1010100 ,
b100 H
1%
#1760000
0%
#1765000
b1010101 !
b1010101 5
b1010101 ,
b101 H
1%
#1770000
0%
#1775000
b1010110 !
b1010110 5
b1010110 ,
b110 H
1%
#1780000
0%
#1785000
b1010111 !
b1010111 5
b1010111 ,
b111 H
1%
#1790000
0%
#1795000
b1011000 !
b1011000 5
b1011000 ,
b1000 H
1%
#1800000
0%
#1805000
b1011001 !
b1011001 5
1J
1?
1*
1-
b1011001 ,
b1001 H
1%
#1810000
0%
#1815000
b11 #
b11 4
b0 !
b0 5
0J
0?
0*
0-
b11 /
b11 A
b0 L
b0 ,
b0 H
1%
#1820000
0%
#1825000
b1 !
b1 5
b1 ,
b1 H
1%
#1830000
0%
#1835000
b10 !
b10 5
b10 ,
b10 H
1%
#1840000
0%
#1845000
b11 !
b11 5
b11 ,
b11 H
1%
#1850000
0%
#1855000
b100 !
b100 5
b100 ,
b100 H
1%
#1860000
0%
#1865000
b101 !
b101 5
b101 ,
b101 H
1%
#1870000
0%
#1875000
b110 !
b110 5
b110 ,
b110 H
1%
#1880000
0%
#1885000
b111 !
b111 5
b111 ,
b111 H
1%
#1890000
0%
#1895000
b1000 !
b1000 5
b1000 ,
b1000 H
1%
#1900000
0%
#1905000
b1001 !
b1001 5
1J
1*
b1001 ,
b1001 H
1%
#1910000
0%
#1915000
b10000 !
b10000 5
0J
0*
b1 L
b10000 ,
b0 H
1%
#1920000
0%
#1925000
b10001 !
b10001 5
b10001 ,
b1 H
1%
#1930000
0%
#1935000
b10010 !
b10010 5
b10010 ,
b10 H
1%
#1940000
0%
#1945000
b10011 !
b10011 5
b10011 ,
b11 H
1%
#1950000
0%
#1955000
b10100 !
b10100 5
b10100 ,
b100 H
1%
#1960000
0%
#1965000
b10101 !
b10101 5
b10101 ,
b101 H
1%
#1970000
0%
#1975000
b10110 !
b10110 5
b10110 ,
b110 H
1%
#1980000
0%
#1985000
b10111 !
b10111 5
b10111 ,
b111 H
1%
#1990000
0%
#1995000
b11000 !
b11000 5
b11000 ,
b1000 H
1%
#2000000
0%
#2005000
b11001 !
b11001 5
1J
1*
b11001 ,
b1001 H
1%
#2010000
0%
#2015000
b100000 !
b100000 5
0J
0*
b10 L
b100000 ,
b0 H
1%
#2020000
0%
#2025000
b100001 !
b100001 5
b100001 ,
b1 H
1%
#2030000
0%
#2035000
b100010 !
b100010 5
b100010 ,
b10 H
1%
#2040000
0%
#2045000
b100011 !
b100011 5
b100011 ,
b11 H
1%
#2050000
0%
#2055000
b100100 !
b100100 5
b100100 ,
b100 H
1%
#2060000
0%
#2065000
b100101 !
b100101 5
b100101 ,
b101 H
1%
#2070000
0%
#2075000
b100110 !
b100110 5
b100110 ,
b110 H
1%
#2080000
0%
#2085000
b100111 !
b100111 5
b100111 ,
b111 H
1%
#2090000
0%
#2095000
b101000 !
b101000 5
b101000 ,
b1000 H
1%
#2100000
0%
#2105000
b101001 !
b101001 5
1J
1*
b101001 ,
b1001 H
1%
#2110000
0%
#2115000
b110000 !
b110000 5
0J
0*
b11 L
b110000 ,
b0 H
1%
#2120000
0%
#2125000
b110001 !
b110001 5
b110001 ,
b1 H
1%
#2130000
0%
#2135000
b110010 !
b110010 5
b110010 ,
b10 H
1%
#2140000
0%
#2145000
b110011 !
b110011 5
b110011 ,
b11 H
1%
#2150000
0%
#2155000
b110100 !
b110100 5
b110100 ,
b100 H
1%
#2160000
0%
#2165000
b110101 !
b110101 5
b110101 ,
b101 H
1%
#2170000
0%
#2175000
b110110 !
b110110 5
b110110 ,
b110 H
1%
#2180000
0%
#2185000
b110111 !
b110111 5
b110111 ,
b111 H
1%
#2190000
0%
#2195000
b111000 !
b111000 5
b111000 ,
b1000 H
1%
#2200000
0%
#2205000
b111001 !
b111001 5
1J
1*
b111001 ,
b1001 H
1%
#2210000
0%
#2215000
b1000000 !
b1000000 5
0J
0*
b100 L
b1000000 ,
b0 H
1%
#2220000
0%
#2225000
b1000001 !
b1000001 5
b1000001 ,
b1 H
1%
#2230000
0%
#2235000
b1000010 !
b1000010 5
b1000010 ,
b10 H
1%
#2240000
0%
#2245000
b1000011 !
b1000011 5
b1000011 ,
b11 H
1%
#2250000
0%
#2255000
b1000100 !
b1000100 5
b1000100 ,
b100 H
1%
#2260000
0%
#2265000
b1000101 !
b1000101 5
b1000101 ,
b101 H
1%
#2270000
0%
#2275000
b1000110 !
b1000110 5
b1000110 ,
b110 H
1%
#2280000
0%
#2285000
b1000111 !
b1000111 5
b1000111 ,
b111 H
1%
#2290000
0%
#2295000
b1001000 !
b1001000 5
b1001000 ,
b1000 H
1%
#2300000
0%
#2305000
b1001001 !
b1001001 5
1J
1*
b1001001 ,
b1001 H
1%
#2310000
0%
#2315000
b1010000 !
b1010000 5
0J
0*
b101 L
b1010000 ,
b0 H
1%
#2320000
0%
#2325000
b1010001 !
b1010001 5
b1010001 ,
b1 H
1%
#2330000
0%
#2335000
b1010010 !
b1010010 5
b1010010 ,
b10 H
1%
#2340000
0%
#2345000
b1010011 !
b1010011 5
b1010011 ,
b11 H
1%
#2350000
0%
#2355000
b1010100 !
b1010100 5
b1010100 ,
b100 H
1%
#2360000
0%
#2365000
b1010101 !
b1010101 5
b1010101 ,
b101 H
1%
#2370000
0%
#2375000
b1010110 !
b1010110 5
b1010110 ,
b110 H
1%
#2380000
0%
#2385000
b1010111 !
b1010111 5
b1010111 ,
b111 H
1%
#2390000
0%
#2395000
b1011000 !
b1011000 5
b1011000 ,
b1000 H
1%
#2400000
0%
#2405000
b1011001 !
b1011001 5
1J
1?
1*
1-
b1011001 ,
b1001 H
1%
#2410000
0%
#2415000
b100 #
b100 4
b0 !
b0 5
0J
0?
0*
0-
b100 /
b100 A
b0 L
b0 ,
b0 H
1%
#2420000
0%
#2425000
b1 !
b1 5
b1 ,
b1 H
1%
#2430000
0%
#2435000
b10 !
b10 5
b10 ,
b10 H
1%
#2440000
0%
#2445000
b11 !
b11 5
b11 ,
b11 H
1%
#2450000
0%
#2455000
b100 !
b100 5
b100 ,
b100 H
1%
#2460000
0%
#2465000
b101 !
b101 5
b101 ,
b101 H
1%
#2470000
0%
#2475000
b110 !
b110 5
b110 ,
b110 H
1%
#2480000
0%
#2485000
b111 !
b111 5
b111 ,
b111 H
1%
#2490000
0%
#2495000
b1000 !
b1000 5
b1000 ,
b1000 H
1%
#2500000
0%
#2505000
b1001 !
b1001 5
1J
1*
b1001 ,
b1001 H
1%
#2510000
0%
#2515000
b10000 !
b10000 5
0J
0*
b1 L
b10000 ,
b0 H
1%
#2520000
0%
#2525000
b10001 !
b10001 5
b10001 ,
b1 H
1%
#2530000
0%
#2535000
b10010 !
b10010 5
b10010 ,
b10 H
1%
#2540000
0%
#2545000
b10011 !
b10011 5
b10011 ,
b11 H
1%
#2550000
0%
#2555000
b10100 !
b10100 5
b10100 ,
b100 H
1%
#2560000
0%
#2565000
b10101 !
b10101 5
b10101 ,
b101 H
1%
#2570000
0%
#2575000
b10110 !
b10110 5
b10110 ,
b110 H
1%
#2580000
0%
#2585000
b10111 !
b10111 5
b10111 ,
b111 H
1%
#2590000
0%
#2595000
b11000 !
b11000 5
b11000 ,
b1000 H
1%
#2600000
0%
#2605000
b11001 !
b11001 5
1J
1*
b11001 ,
b1001 H
1%
#2610000
0%
#2615000
b100000 !
b100000 5
0J
0*
b10 L
b100000 ,
b0 H
1%
#2620000
0%
#2625000
b100001 !
b100001 5
b100001 ,
b1 H
1%
#2630000
0%
#2635000
b100010 !
b100010 5
b100010 ,
b10 H
1%
#2640000
0%
#2645000
b100011 !
b100011 5
b100011 ,
b11 H
1%
#2650000
0%
#2655000
b100100 !
b100100 5
b100100 ,
b100 H
1%
#2660000
0%
#2665000
b100101 !
b100101 5
b100101 ,
b101 H
1%
#2670000
0%
#2675000
b100110 !
b100110 5
b100110 ,
b110 H
1%
#2680000
0%
#2685000
b100111 !
b100111 5
b100111 ,
b111 H
1%
#2690000
0%
#2695000
b101000 !
b101000 5
b101000 ,
b1000 H
1%
#2700000
0%
#2705000
b101001 !
b101001 5
1J
1*
b101001 ,
b1001 H
1%
#2710000
0%
#2715000
b110000 !
b110000 5
0J
0*
b11 L
b110000 ,
b0 H
1%
#2720000
0%
#2725000
b110001 !
b110001 5
b110001 ,
b1 H
1%
#2730000
0%
#2735000
b110010 !
b110010 5
b110010 ,
b10 H
1%
#2740000
0%
#2745000
b110011 !
b110011 5
b110011 ,
b11 H
1%
#2750000
0%
#2755000
b110100 !
b110100 5
b110100 ,
b100 H
1%
#2760000
0%
#2765000
b110101 !
b110101 5
b110101 ,
b101 H
1%
#2770000
0%
#2775000
b110110 !
b110110 5
b110110 ,
b110 H
1%
#2780000
0%
#2785000
b110111 !
b110111 5
b110111 ,
b111 H
1%
#2790000
0%
#2795000
b111000 !
b111000 5
b111000 ,
b1000 H
1%
#2800000
0%
#2805000
b111001 !
b111001 5
1J
1*
b111001 ,
b1001 H
1%
#2810000
0%
#2815000
b1000000 !
b1000000 5
0J
0*
b100 L
b1000000 ,
b0 H
1%
#2820000
0%
#2825000
b1000001 !
b1000001 5
b1000001 ,
b1 H
1%
#2830000
0%
#2835000
b1000010 !
b1000010 5
b1000010 ,
b10 H
1%
#2840000
0%
#2845000
b1000011 !
b1000011 5
b1000011 ,
b11 H
1%
#2850000
0%
